{
  "details": {
    "id": 44,
    "uri": "boska-wloska-zielona-gora",
    "name": "Boska Włoska",
    "kitchens": "Makarony, Pizza, Sałatki",
    "url": "https://pyszne.pl/boska-wloska-zielona-gora"
  },
  "menu": {
    "categories": {
      "O75NQQ77": "Pizza 32 cm",
      "O3PNQQ77": "Sałatki",
      "OPPNQQ77": "Quesadilla",
      "ORPNQQ77": "Dania inne",
      "051O1O1Q": "Napoje bezalkoholowe"
    },
    "popular": [
      "O75375OQQ",
      "O31RR5OQQ",
      "OPP375OQQ"
    ],
    "meals": [
      {
        "productId": "O75375OQQ",
        "categoryId": "O75NQQ77",
        "name": "Pizza Capricciosa",
        "price": 21,
        "price_pickup": 21,
        "hasSizes": true,
        "deliverymethod": 2,
        "is_meal": true
      },
      {
        "productId": "O31RR5OQQ",
        "categoryId": "OPPNQQ77",
        "name": "Quesadilla z kurczakiem",
        "price": 20,
        "price_pickup": 20,
        "hasSizes": false,
        "deliverymethod": 2,
        "is_meal": true
      },
      {
        "productId": "OPP375OQQ",
        "categoryId": "O75NQQ77",
        "name": "Pizza Pio pio",
        "price": 26,
        "price_pickup": 26,
        "hasSizes": true,
        "deliverymethod": 2,
        "is_meal": true
      },
      {
        "productId": "OQO375OQQ",
        "categoryId": "O75NQQ77",
        "name": "Pizza Margherita",
        "price": 17,
        "price_pickup": 17,
        "hasSizes": true,
        "deliverymethod": 2,
        "is_meal": true
      },
      {
        "productId": "O15375OQQ",
        "categoryId": "O75NQQ77",
        "name": "Pizza Costanza",
        "price": 19,
        "price_pickup": 19,
        "hasSizes": true,
        "deliverymethod": 2,
        "is_meal": true
      },
      {
        "productId": "OO5375OQQ",
        "categoryId": "O75NQQ77",
        "name": "Pizza Simplicio",
        "price": 19,
        "price_pickup": 19,
        "hasSizes": true,
        "deliverymethod": 2,
        "is_meal": true
      },
      {
        "productId": "O0P375OQQ",
        "categoryId": "O75NQQ77",
        "name": "Pizza Felicia",
        "price": 20,
        "price_pickup": 20,
        "hasSizes": true,
        "deliverymethod": 2,
        "is_meal": true
      },
      {
        "productId": "O3P375OQQ",
        "categoryId": "O75NQQ77",
        "name": "Pizza Bahama",
        "price": 21,
        "price_pickup": 21,
        "hasSizes": true,
        "deliverymethod": 2,
        "is_meal": true
      },
      {
        "productId": "ORP375OQQ",
        "categoryId": "O75NQQ77",
        "name": "Pizza Giovanna",
        "price": 28,
        "price_pickup": 28,
        "hasSizes": true,
        "deliverymethod": 2,
        "is_meal": true
      },
      {
        "productId": "ON7375OQQ",
        "categoryId": "O75NQQ77",
        "name": "Pizza Messicano",
        "price": 25.5,
        "price_pickup": 25.5,
        "hasSizes": true,
        "deliverymethod": 2,
        "is_meal": true
      },
      {
        "productId": "O57375OQQ",
        "categoryId": "O75NQQ77",
        "name": "Pizza Festa di carne",
        "price": 26,
        "price_pickup": 26,
        "hasSizes": true,
        "deliverymethod": 2,
        "is_meal": true
      },
      {
        "productId": "OQ7375OQQ",
        "categoryId": "O75NQQ77",
        "name": "Pizza Pizza Broccoli",
        "price": 25,
        "price_pickup": 25,
        "hasSizes": true,
        "deliverymethod": 2,
        "is_meal": true
      },
      {
        "productId": "O1Q375OQQ",
        "categoryId": "O75NQQ77",
        "name": "Pizza Quatro Formaggi",
        "price": 27,
        "price_pickup": 27,
        "hasSizes": true,
        "deliverymethod": 2,
        "is_meal": true
      },
      {
        "productId": "OOQ375OQQ",
        "categoryId": "O75NQQ77",
        "name": "Pizza Carbonara",
        "price": 21,
        "price_pickup": 21,
        "hasSizes": true,
        "deliverymethod": 2,
        "is_meal": true
      },
      {
        "productId": "O7Q375OQQ",
        "categoryId": "O75NQQ77",
        "name": "Pizza Vegetariana",
        "price": 27,
        "price_pickup": 27,
        "hasSizes": true,
        "deliverymethod": 2,
        "is_meal": true
      },
      {
        "productId": "O0R375OQQ",
        "categoryId": "O75NQQ77",
        "name": "Pizza Lorenzo",
        "price": 28,
        "price_pickup": 28,
        "hasSizes": true,
        "deliverymethod": 2,
        "is_meal": true
      },
      {
        "productId": "O3R375OQQ",
        "categoryId": "O75NQQ77",
        "name": "Pizza Maurizio",
        "price": 27,
        "price_pickup": 27,
        "hasSizes": true,
        "deliverymethod": 2,
        "is_meal": true
      },
      {
        "productId": "ORR375OQQ",
        "categoryId": "O75NQQ77",
        "name": "Pizza Basilio",
        "price": 24,
        "price_pickup": 24,
        "hasSizes": true,
        "deliverymethod": 2,
        "is_meal": true
      },
      {
        "productId": "ON0O75OQQ",
        "categoryId": "O75NQQ77",
        "name": "Pizza Diavola",
        "price": 28,
        "price_pickup": 28,
        "hasSizes": true,
        "deliverymethod": 2,
        "is_meal": true
      },
      {
        "productId": "O50O75OQQ",
        "categoryId": "O75NQQ77",
        "name": "Pizza Cristoforo",
        "price": 26,
        "price_pickup": 26,
        "hasSizes": true,
        "deliverymethod": 2,
        "is_meal": true
      },
      {
        "productId": "OQ0O75OQQ",
        "categoryId": "O75NQQ77",
        "name": "Pizza Salvatore",
        "price": 26.5,
        "price_pickup": 26.5,
        "hasSizes": true,
        "deliverymethod": 2,
        "is_meal": true
      },
      {
        "productId": "O11O75OQQ",
        "categoryId": "O75NQQ77",
        "name": "Pizza Gambretto",
        "price": 27.5,
        "price_pickup": 27.5,
        "hasSizes": true,
        "deliverymethod": 2,
        "is_meal": true
      },
      {
        "productId": "OO1O75OQQ",
        "categoryId": "O75NQQ77",
        "name": "Pizza Crispino",
        "price": 24,
        "price_pickup": 24,
        "hasSizes": true,
        "deliverymethod": 2,
        "is_meal": true
      },
      {
        "productId": "O71O75OQQ",
        "categoryId": "O75NQQ77",
        "name": "Pizza Tonno e Cipolla",
        "price": 24,
        "price_pickup": 24,
        "hasSizes": true,
        "deliverymethod": 2,
        "is_meal": true
      },
      {
        "productId": "O0NO75OQQ",
        "categoryId": "O75NQQ77",
        "name": "Pizza Paese",
        "price": 24,
        "price_pickup": 24,
        "hasSizes": true,
        "deliverymethod": 2,
        "is_meal": true
      },
      {
        "productId": "O3NO75OQQ",
        "categoryId": "O75NQQ77",
        "name": "Pizza Bianca",
        "price": 24,
        "price_pickup": 24,
        "hasSizes": true,
        "deliverymethod": 2,
        "is_meal": true
      },
      {
        "productId": "OPNO75OQQ",
        "categoryId": "O75NQQ77",
        "name": "Pizza Marinara",
        "price": 26,
        "price_pickup": 26,
        "hasSizes": true,
        "deliverymethod": 2,
        "is_meal": true
      },
      {
        "productId": "ORNO75OQQ",
        "categoryId": "O75NQQ77",
        "name": "Pizza Della Campania",
        "price": 27.5,
        "price_pickup": 27.5,
        "hasSizes": true,
        "deliverymethod": 2,
        "is_meal": true
      },
      {
        "productId": "ON3O75OQQ",
        "categoryId": "O75NQQ77",
        "name": "Pizza E agricoltore",
        "price": 27.5,
        "price_pickup": 27.5,
        "hasSizes": true,
        "deliverymethod": 2,
        "is_meal": true
      },
      {
        "productId": "O53O75OQQ",
        "categoryId": "O75NQQ77",
        "name": "Pizza Cassiano",
        "price": 17,
        "price_pickup": 17,
        "hasSizes": true,
        "deliverymethod": 2,
        "is_meal": true
      },
      {
        "productId": "OQRRQ5OQQ",
        "categoryId": "O3PNQQ77",
        "name": "Sałatka Paradiso degli spinaci",
        "price": 20,
        "price_pickup": 20,
        "hasSizes": false,
        "deliverymethod": 2,
        "is_meal": true
      },
      {
        "productId": "O100R5OQQ",
        "categoryId": "O3PNQQ77",
        "name": "Sałatka Parma",
        "price": 25,
        "price_pickup": 25,
        "hasSizes": false,
        "deliverymethod": 2,
        "is_meal": true
      },
      {
        "productId": "OO00R5OQQ",
        "categoryId": "O3PNQQ77",
        "name": "Sałatka Broccollo",
        "price": 20,
        "price_pickup": 20,
        "hasSizes": false,
        "deliverymethod": 2,
        "is_meal": true
      },
      {
        "productId": "O700R5OQQ",
        "categoryId": "O3PNQQ77",
        "name": "Sałatka Lattuga con camembert",
        "price": 17,
        "price_pickup": 17,
        "hasSizes": false,
        "deliverymethod": 2,
        "is_meal": true
      },
      {
        "productId": "O010R5OQQ",
        "categoryId": "O3PNQQ77",
        "name": "Sałatka Gamberoni",
        "price": 21,
        "price_pickup": 21,
        "hasSizes": false,
        "deliverymethod": 2,
        "is_meal": true
      },
      {
        "productId": "OR10R5OQQ",
        "categoryId": "O3PNQQ77",
        "name": "Sałatka Mozzarella nella foresta",
        "price": 17.5,
        "price_pickup": 17.5,
        "hasSizes": false,
        "deliverymethod": 2,
        "is_meal": true
      },
      {
        "productId": "ONN0R5OQQ",
        "categoryId": "O3PNQQ77",
        "name": "Sałatka Caprese",
        "price": 19,
        "price_pickup": 19,
        "hasSizes": false,
        "deliverymethod": 2,
        "is_meal": true
      },
      {
        "productId": "OP1RR5OQQ",
        "categoryId": "OPPNQQ77",
        "name": "Quesadilla z kurczakiem pikantna",
        "price": 22,
        "price_pickup": 22,
        "hasSizes": false,
        "deliverymethod": 2,
        "is_meal": true
      },
      {
        "productId": "OR1RR5OQQ",
        "categoryId": "OPPNQQ77",
        "name": "Quesadilla 4 sery",
        "price": 22,
        "price_pickup": 22,
        "hasSizes": false,
        "deliverymethod": 2,
        "is_meal": true
      },
      {
        "productId": "ONNRR5OQQ",
        "categoryId": "OPPNQQ77",
        "name": "Quesadilla warzywna",
        "price": 22,
        "price_pickup": 22,
        "hasSizes": false,
        "deliverymethod": 2,
        "is_meal": true
      },
      {
        "productId": "OQ100POQQ",
        "categoryId": "ORPNQQ77",
        "name": "Stripsy z kurczaka",
        "price": 22,
        "price_pickup": 22,
        "hasSizes": false,
        "deliverymethod": 2,
        "is_meal": true
      },
      {
        "productId": "0R7N515QQ",
        "categoryId": "ORPNQQ77",
        "name": "Frytki",
        "price": 7.5,
        "price_pickup": 7.5,
        "hasSizes": false,
        "deliverymethod": 2,
        "is_meal": true
      },
      {
        "productId": "01QN7Q5NR",
        "categoryId": "051O1O1Q",
        "name": "Piwo bezalkoholowe 0.5l Żywiec",
        "price": 9,
        "price_pickup": 9,
        "hasSizes": false,
        "deliverymethod": 2,
        "is_meal": true
      },
      {
        "productId": "0OQN7Q5NR",
        "categoryId": "051O1O1Q",
        "name": "Piwo bezalkoholowe 0.5l Żywiec Białe",
        "price": 9,
        "price_pickup": 9,
        "hasSizes": false,
        "deliverymethod": 2,
        "is_meal": true
      },
      {
        "productId": "07QN7Q5NR",
        "categoryId": "051O1O1Q",
        "name": "Piwo bezalkoholowe 0.5l Warka Radler Jabłko z Mieta",
        "price": 9,
        "price_pickup": 9,
        "hasSizes": false,
        "deliverymethod": 2,
        "is_meal": true
      },
      {
        "productId": "00RN7Q5NR",
        "categoryId": "051O1O1Q",
        "name": "Piwo bezalkoholowe 0.5l Warka Radler Cytrynowe",
        "price": 9,
        "price_pickup": 9,
        "hasSizes": false,
        "deliverymethod": 2,
        "is_meal": true
      },
      {
        "productId": "03RN7Q5NR",
        "categoryId": "051O1O1Q",
        "name": "Piwo bezalkoholowe 0.5l Warka Radler Grejpfrut z Pomarańczą",
        "price": 9,
        "price_pickup": 9,
        "hasSizes": false,
        "deliverymethod": 2,
        "is_meal": true
      }
    ]
  }
}